{
  "mode": {
    "mode": "ge",
    "pending_mode": null
  },
  "queue": {
    "pending": 14,
    "in_progress": 2,
    "done": 0
  },
  "benchmarks": {
    "clr": {
      "clr": 0.769,
      "baseline_clr": 0.19,
      "value_add": 0.579,
      "gate_pass": true,
      "dimensions": {
        "memory_quality": 0.877,
        "retrieval_precision": 0.713,
        "prompt_context": 0.851,
        "task_success": 0.815,
        "autonomy": 0.38,
        "efficiency": 0.986,
        "integration_dynamics": 0.743
      },
      "timestamp": "2026-04-29T05:45:10.411560+00:00"
    },
    "pi": {
      "pi": 0.941,
      "dimensions": 15,
      "timestamp": "2026-04-29T05:45:01.501205+00:00"
    }
  },
  "phi": {
    "current": 0.6141,
    "timestamp": "2026-04-28T18:00:03.436663+00:00"
  },
  "bloat_score": 0.0,
  "brain": {
    "total_memories": 2775,
    "collections": 10
  },
  "episodes": {
    "success_rate": 0.866,
    "total": 500,
    "breakdown": {
      "success": 433,
      "soft_failure": 0,
      "failure": 14,
      "timeout": 4
    }
  },
  "uptime_since": "2026-02-18 12:20:55",
  "recent_completions": [
    {
      "tag": "SPINE_PROXY_REPLACEMENT",
      "status": "success"
    },
    {
      "tag": "SPINE_HOOK_DEPS_MIGRATE",
      "status": "success"
    },
    {
      "tag": "QUEUE_AUTO_ARCHIVE",
      "status": "success"
    },
    {
      "tag": "CRON_CANONICAL_ENTRYPOINTS",
      "status": "success"
    },
    {
      "tag": "OSR_GIT_HISTORY_SCRUB",
      "status": "success"
    }
  ],
  "updated_at": "2026-04-29T05:50:02.263711+00:00"
}