{
  "mode": {
    "mode": "ge",
    "pending_mode": null
  },
  "queue": {
    "pending": 3,
    "in_progress": 3,
    "done": 0
  },
  "benchmarks": {
    "clr": {
      "clr": 0.81,
      "baseline_clr": 0.19,
      "value_add": 0.62,
      "gate_pass": true,
      "dimensions": {
        "memory_quality": 0.63,
        "retrieval_precision": 1.0,
        "prompt_context": 0.748,
        "task_success": 0.789,
        "autonomy": 0.796,
        "efficiency": 0.985,
        "integration_dynamics": 0.864
      },
      "timestamp": "2026-03-30T05:45:12.122090+00:00"
    },
    "pi": {
      "pi": 0.9647,
      "dimensions": 15,
      "timestamp": "2026-03-30T05:45:02.407615+00:00"
    }
  },
  "brain": {
    "total_memories": 2666,
    "collections": 10
  },
  "episodes": {
    "success_rate": 0.811,
    "total": 366,
    "breakdown": {
      "success": 297,
      "soft_failure": 45,
      "failure": 10,
      "timeout": 14
    }
  },
  "uptime_since": "2026-02-18 12:20:37",
  "recent_completions": [
    {
      "tag": "LOAD_SCALING_OPTIMIZE",
      "status": "success"
    },
    {
      "tag": "BENCHMARK_LOAD_NOISE_FLOOR",
      "status": "success"
    },
    {
      "tag": "A5_A7_RUNTIME_MODE_AND_CLI_FINISH",
      "status": "success"
    },
    {
      "tag": "TEMPORAL_RETRIEVAL_FIX",
      "status": "success"
    },
    {
      "tag": "P0_BACKFILL_CREATED_EPOCH_SENTINEL_FIX",
      "status": "success"
    }
  ],
  "updated_at": "2026-03-30T05:50:02.862202+00:00"
}